{
    "exchange": {
        "name": "binance",
        "pair_whitelist": [
            "BTC/USDT",
            "ETH/USDT",
            "XRP/USDT",
            "ADA/USDT",
            "SOL/USDT",
            "DOT/USDT",
            "DOGE/USDT",
            "TRX/USDT",
            "AVAX/USDT",
            "SHIB/USDT",
            "LTC/USDT",
            "MATIC/USDT",
            "FTT/USDT",
            "NEAR/USDT",
            "BCH/USDT",
            "XMR/USDT",
            "XLM/USDT",
            "ETC/USDT",
            "LINK/USDT",
            "ATOM/USDT",
            "ALGO/USDT",
            "FLOW/USDT",
            "UNI/USDT",
            "VET/USDT",
            "TFUEL/USDT",
            "HBAR/USDT",
            "APE/USDT",
            "XTZ/USDT",
            "EGLD/USDT",
            "ICP/USDT",
            "FIL/USDT",
            "SAND/USDT",
            "AXS/USDT",
            "MANA/USDT",
            "AAVE/USDT",
            "EOS/USDT",
            "KLAY/USDT",
            "THETA/USDT",
            "ZEC/USDT",
            "MKR/USDT",
            "GRT/USDT",
            "FTM/USDT",
            "XEC/USDT",
            "QNT/USDT",
            "RUNE/USDT",
            "CAKE/USDT",
            "NEO/USDT",
            "HNT/USDT",
            "NEXO/USDT",
            "ZIL/USDT",
            "AR/USDT",
            "KSM/USDT",
            "GMT/USDT",
            "DASH/USDT",
            "LRC/USDT",
            "CHZ/USDT",
            "CVX/USDT",
            "CELO/USDT",
            "SNX/USDT",
            "AMP/USDT",
            "GALA/USDT",
            "ENJ/USDT",
            "BAT/USDT",
            "STX/USDT",
            "ONE/USDT",
            "GNO/USDT",
            "CRV/USDT",
            "DCR/USDT",
            "KAVA/USDT",
            "MINA/USDT",
            "WAVES/USDT",
            "XEM/USDT",
            "LDO/USDT",
            "HOT/USDT",
            "FXS/USDT",
            "BTG/USDT",
            "QTUM/USDT",
            "KDA/USDT",
            "COMP/USDT",
            "IOST/USDT"
        ]
    },
    "pairlists": [
        {
            "method": "StaticPairList"
        }
    ]
}
